odbserver/__init__.py
odbserver/__main__.py
odbserver/interface.py
pylife_odbserver-2.1.4.dist-info/AUTHORS.rst
pylife_odbserver-2.1.4.dist-info/LICENSE
pylife_odbserver-2.1.4.dist-info/METADATA
pylife_odbserver-2.1.4.dist-info/WHEEL
pylife_odbserver-2.1.4.dist-info/top_level.txt
pylife_odbserver-2.1.4.dist-info/RECORD
