Metadata-Version: 2.1
Name: pylife-odbserver
Version: 2.1.4
Summary: A server for odbAccess to be acessed by pylife-odbclient
Home-page: http://github.com/boschresearch/pylife
Author: Johannes Mueller
Author-email: johannes.mueller4@de.bosch.com
License: Apache-2
Classifier: Programming Language :: Python
Requires-Python: <3
License-File: LICENSE
License-File: AUTHORS.rst
